[
  {
    "username": "doneitp1",
    "password": "$2a$12$KtzAw13C7mNW3cka3OVPwORwnU2qdawcJp.VhDloVblAqnLCp4YjK"
  },
  {
    "username": "qw",
    "password": "$2a$12$d3rk2Vnr.T65MB2XKDHoJ.XHhihcgFJPtK.9iT/ahDcoN6V3v8nt."
  },
  {
    "username": "qede",
    "password": "$2a$12$xb8SMgaKuVuo8B8F0QuZheJwtC8Mp0oxW/NwT/KBvneJbQewyNjUO"
  },
  {
    "username": "edfe",
    "password": "$2a$12$NmxW3HCtNEtiE4WcnfXf8.C51PtOxSnQHYVgqfEYNzQsOaE2VHmUm"
  },
  {
    "username": "qwe",
    "password": "$2a$12$dfuxsG8MxHcG8WEUo.n0hexvtsWnvdr2VUHl5f483dsmhiSg7ijQi"
  },
  {
    "username": "ccwevwr",
    "password": "$2a$12$Lx6Hx1LzuI0EjwtQXwlkkeH3jh3xQSBqu2qiwgdWY3.HPXjadj8pi"
  },
  {
    "username": "qwq",
    "password": "$2a$12$O4yTRdGfB/39wluIfGBRLO9h9LX4hRzqYvSeLpW1vwza5GmhI24SW"
  }
]